{
  "name": "angelsindustries",
  "version": "0.4.8",
  "factorio_version": "1.0",
  "title": "Angel's Industries",
  "author": "Arch666Angel",
  "contact": "https://discord.gg/ff5p6KE",
  "homepage": "https://forums.factorio.com/viewforum.php?f=185",
  "description": "Adds industrial equipment as well as the tools you need to expand and grow your base. Adds extra components [BETA] and a tech [ALPHA] overhaul.",
  "dependencies": [
    "base >= 1.0.0",

    "angelsrefining >= 0.11.18",
    "angelspetrochem >= 0.9.16",
    "angelssmelting >= 0.6.13",
    "angelsbioprocessing >= 0.7.16",

    "(?) bobassembly >= 0.18.6",
    "(?) boblogistics >= 1.0.0",
    "(?) bobtech >= 0.18.3",
    "(?) bobrevamp >= 0.18.5",

    "(?) aai-industry >= 0.4.12"
  ]
}
